odoo/addons/sale_fixed_discount/README.rst
odoo/addons/sale_fixed_discount/__init__.py
odoo/addons/sale_fixed_discount/__manifest__.py
odoo/addons/sale_fixed_discount/i18n/es.po
odoo/addons/sale_fixed_discount/i18n/fr.po
odoo/addons/sale_fixed_discount/i18n/it.po
odoo/addons/sale_fixed_discount/i18n/pt_BR.po
odoo/addons/sale_fixed_discount/i18n/sale_fixed_discount.pot
odoo/addons/sale_fixed_discount/models/__init__.py
odoo/addons/sale_fixed_discount/models/sale_order_line.py
odoo/addons/sale_fixed_discount/readme/CONFIGURE.md
odoo/addons/sale_fixed_discount/readme/CONTRIBUTORS.md
odoo/addons/sale_fixed_discount/readme/DESCRIPTION.md
odoo/addons/sale_fixed_discount/readme/INSTALL.md
odoo/addons/sale_fixed_discount/readme/USAGE.md
odoo/addons/sale_fixed_discount/reports/report_sale_order.xml
odoo/addons/sale_fixed_discount/security/res_groups.xml
odoo/addons/sale_fixed_discount/static/description/icon.png
odoo/addons/sale_fixed_discount/static/description/index.html
odoo/addons/sale_fixed_discount/tests/__init__.py
odoo/addons/sale_fixed_discount/tests/test_sale_fixed_discount.py
odoo/addons/sale_fixed_discount/views/account_invoice_views.xml
odoo/addons/sale_fixed_discount/views/sale_order_views.xml
odoo/addons/sale_fixed_discount/views/sale_portal_templates.xml
odoo_addon_sale_fixed_discount-18.0.1.0.0.2.dist-info/METADATA
odoo_addon_sale_fixed_discount-18.0.1.0.0.2.dist-info/WHEEL
odoo_addon_sale_fixed_discount-18.0.1.0.0.2.dist-info/top_level.txt
odoo_addon_sale_fixed_discount-18.0.1.0.0.2.dist-info/RECORD
